famlafl/__init__.py
famlafl/backtest_statistics/__init__.py
famlafl/backtest_statistics/backtests.py
famlafl/backtest_statistics/statistics.py
famlafl/bet_sizing/README.md
famlafl/bet_sizing/__init__.py
famlafl/bet_sizing/bet_sizing.py
famlafl/bet_sizing/ch10_snippets.py
famlafl/bet_sizing/ef3m.py
famlafl/clustering/__init__.py
famlafl/clustering/feature_clusters.py
famlafl/clustering/onc.py
famlafl/codependence/__init__.py
famlafl/codependence/codependence_matrix.py
famlafl/codependence/correlation.py
famlafl/codependence/gnpr_distance.py
famlafl/codependence/information.py
famlafl/cross_validation/__init__.py
famlafl/cross_validation/combinatorial.py
famlafl/cross_validation/cross_validation.py
famlafl/data_structures/__init__.py
famlafl/data_structures/base_bars.py
famlafl/data_structures/imbalance_data_structures.py
famlafl/data_structures/run_data_structures.py
famlafl/data_structures/standard_data_structures.py
famlafl/data_structures/time_data_structures.py
famlafl/datasets/__init__.py
famlafl/datasets/data/dollar_bar_sample.csv
famlafl/datasets/data/stock_prices.csv
famlafl/datasets/data/tick_data.csv
famlafl/datasets/load_datasets.py
famlafl/ensemble/__init__.py
famlafl/ensemble/sb_bagging.py
famlafl/feature_importance/__init__.py
famlafl/feature_importance/fingerpint.py
famlafl/feature_importance/importance.py
famlafl/feature_importance/orthogonal.py
famlafl/features/__init__.py
famlafl/features/fracdiff.py
famlafl/filters/__init__.py
famlafl/filters/filters.py
famlafl/labeling/__init__.py
famlafl/labeling/excess_over_mean.py
famlafl/labeling/excess_over_median.py
famlafl/labeling/fixed_time_horizon.py
famlafl/labeling/labeling.py
famlafl/labeling/matrix_flags.py
famlafl/labeling/raw_return.py
famlafl/labeling/return_vs_benchmark.py
famlafl/labeling/tail_sets.py
famlafl/labeling/trend_scanning.py
famlafl/microstructural_features/__init__.py
famlafl/microstructural_features/encoding.py
famlafl/microstructural_features/entropy.py
famlafl-0.1.9.dist-info/LICENSE
famlafl-0.1.9.dist-info/METADATA
famlafl-0.1.9.dist-info/WHEEL
famlafl-0.1.9.dist-info/entry_points.txt
famlafl-0.1.9.dist-info/RECORD
